{
  "author": {
    "id": "t2_3szwe",
    "name": "davema"
  },
  "date": {
    "day": 1521590400,
    "full": 1521648863,
    "month": 1519862400,
    "week": 1521331200
  },
  "id": "t3_863c12",
  "misc": {
    "postHint": "link"
  },
  "picture": {
    "full": "https://external-preview.redd.it/mgmY9AW7vZ9Lowmmy0DnrLQuJy8GT1oQyBGA_2ip_Xs.gif?format=png8&s=37b184beb6f35d396d2175ed67063084b7d9d4c9",
    "preview": "https://external-preview.redd.it/mgmY9AW7vZ9Lowmmy0DnrLQuJy8GT1oQyBGA_2ip_Xs.gif?width=640&crop=smart&format=png8&s=e6b84208581fe5ebeb01bd97e5aa5a1a9feb43c5",
    "thumbnail": "https://a.thumbs.redditmedia.com/csDElmUiSYOgIAeOsyNxMTfTxom_FYhdiyp57K5so38.jpg"
  },
  "score": {
    "comments": 17,
    "downs": 0,
    "isCurated": false,
    "ratio": 0.98,
    "ups": 352,
    "value": 352
  },
  "subreddit": {
    "id": "t5_2xy5e",
    "name": "TerrainBuilding"
  },
  "tags": [],
  "title": "Power Generator for 40k",
  "url": "https://www.reddit.com/r/TerrainBuilding/comments/863c12/power_generator_for_40k/"
}
