{
  "author": {
    "id": "t2_aon9g",
    "name": "Rymotron"
  },
  "date": {
    "day": 1604707200,
    "full": 1604774329,
    "month": 1604188800,
    "week": 1604188800
  },
  "id": "t3_jpvko6",
  "misc": {
    "postHint": "link"
  },
  "picture": {
    "full": "https://external-preview.redd.it/ZvNQqssbNM_SgrFSZZy1wU1VphWiRodg4EHGBg5HupQ.jpg?auto=webp&s=a5497f66098756faf2e00341646e8553bf298279",
    "preview": "https://external-preview.redd.it/ZvNQqssbNM_SgrFSZZy1wU1VphWiRodg4EHGBg5HupQ.jpg?width=640&crop=smart&auto=webp&s=4b87335e765e15576f89a86b684d57f58b37fb69",
    "thumbnail": "https://b.thumbs.redditmedia.com/JHoII4_gFi1V92thoTgdq3iqiD-EH7y8FpdyvWbb_dA.jpg"
  },
  "score": {
    "comments": 0,
    "downs": 0,
    "isCurated": false,
    "ratio": 1,
    "ups": 16,
    "value": 16
  },
  "subreddit": {
    "id": "t5_2xy5e",
    "name": "TerrainBuilding"
  },
  "tags": [],
  "title": "First piece of Warcry terrain complete! Really proud of this one!",
  "url": "https://www.reddit.com/r/TerrainBuilding/comments/jpvko6/first_piece_of_warcry_terrain_complete_really/"
}
