{
  "author": {
    "id": "t2_3umo3flw",
    "name": "Cyberhaggis"
  },
  "date": {
    "day": 1606435200,
    "full": 1606510609,
    "month": 1604188800,
    "week": 1606003200
  },
  "id": "t3_k29i6v",
  "misc": {
    "postHint": "image"
  },
  "picture": {
    "full": "https://external-preview.redd.it/TA_3Sf45r8zRtWQPr7xBhEJeSZ3R0R86zvgCGpoLmRo.jpg?auto=webp&s=d8e30de31932fdd114c1b8e3b727d7fb408f5623",
    "preview": "https://external-preview.redd.it/TA_3Sf45r8zRtWQPr7xBhEJeSZ3R0R86zvgCGpoLmRo.jpg?width=640&crop=smart&auto=webp&s=f3496b189f349f81602f65f2d863f90bd71b00e9",
    "thumbnail": "https://b.thumbs.redditmedia.com/6TiJaetfQh2WMVUz9G0AZRaQVlUWjvrG5ZqWAVuik1I.jpg"
  },
  "score": {
    "comments": 4,
    "downs": 0,
    "isCurated": false,
    "ratio": 0.97,
    "ups": 81,
    "value": 81
  },
  "subreddit": {
    "id": "t5_2xy5e",
    "name": "TerrainBuilding"
  },
  "tags": [],
  "title": "Necromancer's Lair WIP",
  "url": "https://www.reddit.com/r/TerrainBuilding/comments/k29i6v/necromancers_lair_wip/"
}
