{
  "author": {
    "id": "t2_16yt4o",
    "name": "Scortas"
  },
  "date": {
    "day": 1573084800,
    "full": 1573161484,
    "month": 1572566400,
    "week": 1572739200
  },
  "id": "t3_dt4h92",
  "misc": {
    "postHint": "self"
  },
  "picture": {
    "full": "https://external-preview.redd.it/AzbxlST57eP1U2dY24e4wst1jyMqBe_AaXB9B8gJ1pI.jpg?auto=webp&s=5c58f9c33f8709658532442e276810d610e87244",
    "preview": "https://external-preview.redd.it/AzbxlST57eP1U2dY24e4wst1jyMqBe_AaXB9B8gJ1pI.jpg?width=640&crop=smart&auto=webp&s=5b8c4db86914ef554abfb9b57f3806b46ce893a6",
    "thumbnail": "self"
  },
  "score": {
    "comments": 2,
    "downs": 0,
    "isCurated": false,
    "ratio": 0.88,
    "ups": 6,
    "value": 6
  },
  "subreddit": {
    "id": "t5_2xy5e",
    "name": "TerrainBuilding"
  },
  "tags": [],
  "title": "Need Help 1st time Terrain for DnD",
  "url": "https://www.reddit.com/r/TerrainBuilding/comments/dt4h92/need_help_1st_time_terrain_for_dnd/"
}
