{
  "author": {
    "id": "t2_t0oag",
    "name": "Rudizzl0r"
  },
  "date": {
    "day": 1534636800,
    "full": 1534674981,
    "month": 1533081600,
    "week": 1534636800
  },
  "id": "t3_98jea6",
  "misc": {
    "postHint": "link"
  },
  "picture": {
    "full": "https://external-preview.redd.it/wQBsmJyZO4hY_Do6Gj07xnEz70nRxqX0Prp0zjc8kCM.jpg?auto=webp&s=124dcb73b64ba311c9c5be38243facb02addf71f",
    "preview": "https://external-preview.redd.it/wQBsmJyZO4hY_Do6Gj07xnEz70nRxqX0Prp0zjc8kCM.jpg?width=640&crop=smart&auto=webp&s=e73f2dd2e3d692756a643a00fe6f1eda2a1b50b6",
    "thumbnail": "https://b.thumbs.redditmedia.com/usiec0CjekwLmp1aywJXCmyEu36drivjkku_Hcu58wA.jpg"
  },
  "score": {
    "comments": 3,
    "downs": 0,
    "isCurated": false,
    "ratio": 0.96,
    "ups": 42,
    "value": 42
  },
  "subreddit": {
    "id": "t5_2xy5e",
    "name": "TerrainBuilding"
  },
  "tags": [],
  "title": "Some 40k terrain i made from cardboard, clay and rubbish C&C welcome",
  "url": "https://www.reddit.com/r/TerrainBuilding/comments/98jea6/some_40k_terrain_i_made_from_cardboard_clay_and/"
}
