{
  "author": {
    "id": "t2_ayvtbm",
    "name": "PandarineXXL"
  },
  "date": {
    "day": 1563580800,
    "full": 1563624567,
    "month": 1561939200,
    "week": 1563062400
  },
  "id": "t3_cfl4qg",
  "misc": {
    "postHint": "link"
  },
  "picture": {
    "full": "https://external-preview.redd.it/imyLwOebGITwNBKxFCAm0TAJovdA-BUwT1geot2iQoc.jpg?auto=webp&s=1b11d85bd4f66c6351a1d06fa0fbb1d5254deda5",
    "preview": "https://external-preview.redd.it/imyLwOebGITwNBKxFCAm0TAJovdA-BUwT1geot2iQoc.jpg?width=640&crop=smart&auto=webp&s=1d5718640c856bbed280028d0ce0184d24a48706",
    "thumbnail": "https://b.thumbs.redditmedia.com/BUwmMi9qRv9jiVTpgQMcHrvfUnBADRTFUeLxuX6Hsgk.jpg"
  },
  "score": {
    "comments": 3,
    "downs": 0,
    "isCurated": false,
    "ratio": 1,
    "ups": 10,
    "value": 10
  },
  "subreddit": {
    "id": "t5_2xy5e",
    "name": "TerrainBuilding"
  },
  "tags": [],
  "title": "Looking for Volcano Tutorial/Tips",
  "url": "https://www.reddit.com/r/TerrainBuilding/comments/cfl4qg/looking_for_volcano_tutorialtips/"
}
