{
  "author": {
    "id": "t2_jih4h",
    "name": "mrshinra83"
  },
  "date": {
    "day": 1522800000,
    "full": 1522874490,
    "month": 1522540800,
    "week": 1522540800
  },
  "id": "t3_89ta1b",
  "misc": {
    "postHint": "image"
  },
  "picture": {
    "full": "https://preview.redd.it/80u08huccyp01.jpg?auto=webp&s=3691712a758884dd8d89faecaf71412fd1e4db7c",
    "preview": "https://preview.redd.it/80u08huccyp01.jpg?width=640&crop=smart&auto=webp&s=6771eec2ce323ff2276080d995c78063b0289510",
    "thumbnail": "https://b.thumbs.redditmedia.com/si9FVm2Iog_k34E4fEQxSLa0VBWKznNE43I89zyNyKQ.jpg"
  },
  "score": {
    "comments": 39,
    "downs": 0,
    "isCurated": false,
    "ratio": 0.93,
    "ups": 48,
    "value": 48
  },
  "subreddit": {
    "id": "t5_2xy5e",
    "name": "TerrainBuilding"
  },
  "tags": [],
  "title": "Newbie scared of looking silly- Are these wood blocks \"faux pas\" or suitable to mod for battle?",
  "url": "https://www.reddit.com/r/TerrainBuilding/comments/89ta1b/newbie_scared_of_looking_silly_are_these_wood/"
}
