{
  "author": {
    "id": "t2_1ncf2bmw",
    "name": "Tony_Balogne"
  },
  "date": {
    "day": 1600300800,
    "full": 1600360790,
    "month": 1598918400,
    "week": 1599955200
  },
  "id": "t3_iun4u3",
  "misc": {
    "postHint": "image"
  },
  "picture": {
    "full": "https://preview.redd.it/pxo07d1rkqn51.jpg?auto=webp&s=f2450305b1d9aad67a0879217d11aa25c50996af",
    "preview": "https://preview.redd.it/pxo07d1rkqn51.jpg?width=640&crop=smart&auto=webp&s=f46b602add5961295b2af5245973d00d5f14a1b6",
    "thumbnail": "https://b.thumbs.redditmedia.com/AAMuMyypzf3uL9HIyBGPIYc2He8TYROep5sO2r08v6Y.jpg"
  },
  "score": {
    "comments": 30,
    "downs": 0,
    "isCurated": false,
    "ratio": 0.99,
    "ups": 974,
    "value": 974
  },
  "subreddit": {
    "id": "t5_2xy5e",
    "name": "TerrainBuilding"
  },
  "tags": [],
  "title": "Built this water tower for Gaslands from scratch",
  "url": "https://www.reddit.com/r/TerrainBuilding/comments/iun4u3/built_this_water_tower_for_gaslands_from_scratch/"
}
