{
  "author": {
    "id": "t2_5n8pt",
    "name": "MonkeykingZX"
  },
  "date": {
    "day": 1599782400,
    "full": 1599850520,
    "month": 1598918400,
    "week": 1599350400
  },
  "id": "t3_iqwt1t",
  "misc": {
    "postHint": "image"
  },
  "picture": {
    "full": "https://preview.redd.it/53a9cj6efkm51.png?auto=webp&s=072a5da88b36c3ffeab320bfb57061377e164b6a",
    "preview": "https://preview.redd.it/53a9cj6efkm51.png?width=640&crop=smart&auto=webp&s=3348af5b1f1ca431c5857b744f979a91f5fbb9a7",
    "thumbnail": "https://a.thumbs.redditmedia.com/tf9jmQL7NnJyOismLAG54khWLVmgg2Yv6gttbwIxQJ8.jpg"
  },
  "score": {
    "comments": 20,
    "downs": 0,
    "isCurated": false,
    "ratio": 1,
    "ups": 661,
    "value": 661
  },
  "subreddit": {
    "id": "t5_2xy5e",
    "name": "TerrainBuilding"
  },
  "tags": [],
  "title": "Terrain setup for a narrative siege game of 40k tomorrow",
  "url": "https://www.reddit.com/r/TerrainBuilding/comments/iqwt1t/terrain_setup_for_a_narrative_siege_game_of_40k/"
}
