{
  "author": {
    "id": "t2_ae6vkon",
    "name": "gufted"
  },
  "date": {
    "day": 1600819200,
    "full": 1600839662,
    "month": 1598918400,
    "week": 1600560000
  },
  "id": "t3_iy4eyf",
  "misc": {
    "postHint": "image"
  },
  "picture": {
    "full": "https://preview.redd.it/l3svqb5o4uo51.jpg?auto=webp&s=165ce833feb71e7b8b46a442b5b1af8565998e42",
    "preview": "https://preview.redd.it/l3svqb5o4uo51.jpg?width=640&crop=smart&auto=webp&s=88d48bc80fc6eace1541c37c82d357f121496628",
    "thumbnail": "https://b.thumbs.redditmedia.com/xvqwbGF2i7ytzgtU8M-byamzhmPnt4QtC8QgZHPaYWI.jpg"
  },
  "score": {
    "comments": 2,
    "downs": 0,
    "isCurated": false,
    "ratio": 0.97,
    "ups": 45,
    "value": 45
  },
  "subreddit": {
    "id": "t5_2xy5e",
    "name": "TerrainBuilding"
  },
  "tags": [],
  "title": "Tree collection - DIY hard sponge & clay",
  "url": "https://www.reddit.com/r/TerrainBuilding/comments/iy4eyf/tree_collection_diy_hard_sponge_clay/"
}
