{
  "author": {
    "id": "t2_5zqqv",
    "name": "TheAngryRed"
  },
  "date": {
    "day": 1600473600,
    "full": 1600477832,
    "month": 1598918400,
    "week": 1599955200
  },
  "id": "t3_ivisha",
  "misc": {
    "postHint": "self"
  },
  "picture": {
    "full": "https://external-preview.redd.it/xWTk9Q6Mf8sA3k6qduRwLWzBLTW-r_xwniNuMEbj7rU.jpg?auto=webp&s=61ba7631e8d4c9464732bfea8801a0d8d0783e9c",
    "preview": "https://external-preview.redd.it/xWTk9Q6Mf8sA3k6qduRwLWzBLTW-r_xwniNuMEbj7rU.jpg?width=640&crop=smart&auto=webp&s=473380bbf2945f948c7805e694eabb1204f6b884",
    "thumbnail": "self"
  },
  "score": {
    "comments": 10,
    "downs": 0,
    "isCurated": false,
    "ratio": 1,
    "ups": 10,
    "value": 10
  },
  "subreddit": {
    "id": "t5_2xy5e",
    "name": "TerrainBuilding"
  },
  "tags": [],
  "title": "Best materials to use for laying bundles of power cables or wires?",
  "url": "https://www.reddit.com/r/TerrainBuilding/comments/ivisha/best_materials_to_use_for_laying_bundles_of_power/"
}
