{
  "author": {
    "id": "t2_657f8",
    "name": "cheezewizz2000"
  },
  "date": {
    "day": 1601424000,
    "full": 1601452693,
    "month": 1598918400,
    "week": 1601164800
  },
  "id": "t3_j2hzh5",
  "misc": {
    "postHint": "image"
  },
  "picture": {
    "full": "https://preview.redd.it/k77ykgojr8q51.jpg?auto=webp&s=6e5a99c245a42ab8af0cd8233bc593da7592a243",
    "preview": "https://preview.redd.it/k77ykgojr8q51.jpg?width=640&crop=smart&auto=webp&s=ac52c32e34a99e58dec549c7846640d748aed019",
    "thumbnail": "https://b.thumbs.redditmedia.com/QFIl-aXs0IyZHxdCsp3IV4Qj_TGvv0Qw6ENGmFXIx5g.jpg"
  },
  "score": {
    "comments": 9,
    "downs": 0,
    "isCurated": false,
    "ratio": 0.99,
    "ups": 137,
    "value": 137
  },
  "subreddit": {
    "id": "t5_2xy5e",
    "name": "TerrainBuilding"
  },
  "tags": [],
  "title": "TT combat's Ponte Leone painted. Any ideas for additions and weathering?",
  "url": "https://www.reddit.com/r/TerrainBuilding/comments/j2hzh5/tt_combats_ponte_leone_painted_any_ideas_for/"
}
