{
  "author": {
    "id": "t2_5lvyngfn",
    "name": "Mr-Seraphon-Skink"
  },
  "date": {
    "day": 1601251200,
    "full": 1601334965,
    "month": 1598918400,
    "week": 1601164800
  },
  "id": "t3_j1nbdl",
  "misc": {
    "postHint": "image"
  },
  "picture": {
    "full": "https://preview.redd.it/h1huvy5h1zp51.jpg?auto=webp&s=9d398a9d903f4fe662bc8159d77f1e16f2c3d231",
    "preview": "https://preview.redd.it/h1huvy5h1zp51.jpg?width=640&crop=smart&auto=webp&s=39af7ca7e4ca55ff10952b153c7b6172472772fb",
    "thumbnail": "https://b.thumbs.redditmedia.com/GmDmWezeL7cffQkae7ajKVUPrrOueFW3TWwZkruhhmk.jpg"
  },
  "score": {
    "comments": 0,
    "downs": 0,
    "isCurated": false,
    "ratio": 0.96,
    "ups": 19,
    "value": 19
  },
  "subreddit": {
    "id": "t5_2xy5e",
    "name": "TerrainBuilding"
  },
  "tags": [],
  "title": "A watchtower i made out of balsa wood and a pringles tin",
  "url": "https://www.reddit.com/r/TerrainBuilding/comments/j1nbdl/a_watchtower_i_made_out_of_balsa_wood_and_a/"
}
