{
  "author": {
    "id": "t2_48svn",
    "name": "richardathome"
  },
  "date": {
    "day": 1483833600,
    "full": 1483896360,
    "month": 1483228800,
    "week": 1483833600
  },
  "id": "t3_5mrxaz",
  "misc": {
    "postHint": "link"
  },
  "picture": {
    "full": "https://external-preview.redd.it/ZMHoyweq0kjCVhH0qIGh7_Y7yDNMA770fJP3b8d1Jgo.jpg?auto=webp&s=00dbc239f66809a8f572f3d316b953b0a6b2b7df",
    "preview": "https://external-preview.redd.it/ZMHoyweq0kjCVhH0qIGh7_Y7yDNMA770fJP3b8d1Jgo.jpg?width=640&crop=smart&auto=webp&s=e430d493ea2bd45bba0ecb4f8677ccbe8c3310f9",
    "thumbnail": "https://b.thumbs.redditmedia.com/hAHzvg0OsYQk6qxCZMwmfwWUw-_V6WBnXgT8Sh3JqXI.jpg"
  },
  "score": {
    "comments": 7,
    "downs": 0,
    "isCurated": false,
    "ratio": 1,
    "ups": 77,
    "value": 77
  },
  "subreddit": {
    "id": "t5_2xy5e",
    "name": "TerrainBuilding"
  },
  "tags": [],
  "title": "Scratchbuilt Frostgrave Terrain: 4 Door Crypt",
  "url": "https://www.reddit.com/r/TerrainBuilding/comments/5mrxaz/scratchbuilt_frostgrave_terrain_4_door_crypt/"
}
