{
  "author": {
    "id": "t2_2boc1zjv",
    "name": "sebastiankussowski"
  },
  "date": {
    "day": 1608940800,
    "full": 1608986335,
    "month": 1606780800,
    "week": 1608422400
  },
  "id": "t3_kkhzpd",
  "misc": {
    "postHint": "hosted:video"
  },
  "picture": {
    "full": "https://external-preview.redd.it/0YIbRHNqD0IT68gZrM5hYU8nSa2PoJJYCF_LePHnkpM.png?format=pjpg&auto=webp&s=1a5edd6256ea4ea37605dd89673908909c8db26f",
    "preview": "https://external-preview.redd.it/0YIbRHNqD0IT68gZrM5hYU8nSa2PoJJYCF_LePHnkpM.png?width=640&crop=smart&format=pjpg&auto=webp&s=13a8234f32b7be470cc69aa940ae589993e5594b",
    "thumbnail": "https://b.thumbs.redditmedia.com/QHFPmR8jfvofA02hiuWibghUZl1aduVFo9JI6iejIRw.jpg"
  },
  "score": {
    "comments": 14,
    "downs": 0,
    "isCurated": false,
    "ratio": 0.99,
    "ups": 600,
    "value": 600
  },
  "subreddit": {
    "id": "t5_2xy5e",
    "name": "TerrainBuilding"
  },
  "tags": [],
  "title": "I made some Ice Cavern terrain for Rime of the frostmaiden! Full Video: https://youtu.be/7wtwDWa2i5s",
  "url": "https://www.reddit.com/r/TerrainBuilding/comments/kkhzpd/i_made_some_ice_cavern_terrain_for_rime_of_the/"
}
