{
  "author": {
    "id": "t2_4qous5pj",
    "name": "buildthemechs"
  },
  "date": {
    "day": 1603497600,
    "full": 1603575493,
    "month": 1601510400,
    "week": 1602979200
  },
  "id": "t3_jhhadd",
  "misc": {
    "postHint": "hosted:video"
  },
  "picture": {
    "full": "https://external-preview.redd.it/m1xD6sKHzPY7ADtrwNUeRjbE6WcXRiJy3PfuDDgumXc.png?format=pjpg&auto=webp&s=06d4fa7cfb058d7fe947ff699e24f83ad4573deb",
    "preview": "https://external-preview.redd.it/m1xD6sKHzPY7ADtrwNUeRjbE6WcXRiJy3PfuDDgumXc.png?width=640&crop=smart&format=pjpg&auto=webp&s=9020e4623144fe359bc1417d7b2e3deb29f684b4",
    "thumbnail": "https://b.thumbs.redditmedia.com/W8qwItjO6U-4t9xM2Ewox-5CMs7P5HbT1u0jEtQ3g5Q.jpg"
  },
  "score": {
    "comments": 10,
    "downs": 0,
    "isCurated": false,
    "ratio": 1,
    "ups": 399,
    "value": 399
  },
  "subreddit": {
    "id": "t5_2xy5e",
    "name": "TerrainBuilding"
  },
  "tags": [],
  "title": "Just finished another project! This one is a secure storage bay with laser gates and interior lights. You can find a link to the build gallery in the comments.",
  "url": "https://www.reddit.com/r/TerrainBuilding/comments/jhhadd/just_finished_another_project_this_one_is_a/"
}
