{
  "author": {
    "id": "t2_87irold",
    "name": "TotesMcGotes87"
  },
  "date": {
    "day": 1601596800,
    "full": 1601639542,
    "month": 1601510400,
    "week": 1601164800
  },
  "id": "t3_j3t2zl",
  "misc": {
    "postHint": "image"
  },
  "picture": {
    "full": "https://preview.redd.it/ih4007357oq51.jpg?auto=webp&s=a125e1541ea4a521967926a157dafe1f37392e54",
    "preview": "https://preview.redd.it/ih4007357oq51.jpg?width=640&crop=smart&auto=webp&s=bf8fc1b643715c3e45dafbb9aac00821033a7ed8",
    "thumbnail": "https://a.thumbs.redditmedia.com/76gPaUrUeh2Mxkc-_9N-N8GewlDGnogz7JzPfRxuC-0.jpg"
  },
  "score": {
    "comments": 17,
    "downs": 0,
    "isCurated": false,
    "ratio": 1,
    "ups": 239,
    "value": 239
  },
  "subreddit": {
    "id": "t5_2xy5e",
    "name": "TerrainBuilding"
  },
  "tags": [],
  "title": "WIP of my woodland terrain pieces. I’d like a few more trees but still need space to put minis in there when required. Gluing in the trees and then adding some grass tufts is the plan.",
  "url": "https://www.reddit.com/r/TerrainBuilding/comments/j3t2zl/wip_of_my_woodland_terrain_pieces_id_like_a_few/"
}
