{
  "author": {
    "id": "t2_5ozm29yi",
    "name": "scathappens"
  },
  "date": {
    "day": 1603756800,
    "full": 1603835699,
    "month": 1601510400,
    "week": 1603584000
  },
  "id": "t3_jjavlm",
  "misc": {
    "postHint": "image"
  },
  "picture": {
    "full": "https://preview.redd.it/3c3ee0sdlpv51.jpg?auto=webp&s=d96811f7b9ea51493edc32633c4a742129f4c6d1",
    "preview": "https://preview.redd.it/3c3ee0sdlpv51.jpg?width=640&crop=smart&auto=webp&s=ff25a562e330c5bb0dbc94c424228f02e9ece135",
    "thumbnail": "https://b.thumbs.redditmedia.com/U9Zpmg4PJAoWGHoGvew0vOT6YYfbvJ6M_qlK40jGaIY.jpg"
  },
  "score": {
    "comments": 0,
    "downs": 0,
    "isCurated": false,
    "ratio": 0.99,
    "ups": 15,
    "value": 15
  },
  "subreddit": {
    "id": "t5_2xy5e",
    "name": "TerrainBuilding"
  },
  "tags": [],
  "title": "It's been a busy day painting up a storm, the table is nearly ready to put together, can't wait to see how it looks. Great set of tiles from Digital Taxidermy",
  "url": "https://www.reddit.com/r/TerrainBuilding/comments/jjavlm/its_been_a_busy_day_painting_up_a_storm_the_table/"
}
