{
  "author": {
    "id": "t2_106mw9xf",
    "name": "modellismofantasy"
  },
  "date": {
    "day": 1585958400,
    "full": 1586033945,
    "month": 1585699200,
    "week": 1585440000
  },
  "id": "t3_fv17oo",
  "misc": {
    "postHint": "image"
  },
  "picture": {
    "full": "https://preview.redd.it/i47vg6vl7vq41.jpg?auto=webp&s=8461c6b9c16b55616e0092ae3f793e495e3f83f5",
    "preview": "https://preview.redd.it/i47vg6vl7vq41.jpg?width=640&crop=smart&auto=webp&s=bd9ce5e7ea6181018732c67e31dc8484143265af",
    "thumbnail": "https://b.thumbs.redditmedia.com/ViVm9nd7-4sIPRSSiP1fG8KKDmEaf3c-eB3eKQS2AZc.jpg"
  },
  "score": {
    "comments": 6,
    "downs": 0,
    "isCurated": false,
    "ratio": 0.94,
    "ups": 56,
    "value": 56
  },
  "subreddit": {
    "id": "t5_2xy5e",
    "name": "TerrainBuilding"
  },
  "tags": [],
  "title": "Fantasy Grocery for D&D, in XPS Foam. Complete gallery in the comments.",
  "url": "https://www.reddit.com/r/TerrainBuilding/comments/fv17oo/ocfantasy_grocery_for_dd_in_xps_foam_complete/"
}
