{
  "author": {
    "id": "t2_2cocyhzc",
    "name": "lukeousj92"
  },
  "date": {
    "day": 1587427200,
    "full": 1587463310,
    "month": 1585699200,
    "week": 1587254400
  },
  "id": "t3_g5ch9k",
  "misc": {
    "postHint": "image"
  },
  "picture": {
    "full": "https://preview.redd.it/jf89tmhx95u41.jpg?auto=webp&s=114be22694f30a08ab9793ae184ac7e6d07e7282",
    "preview": "https://preview.redd.it/jf89tmhx95u41.jpg?width=640&crop=smart&auto=webp&s=3222a806c3fb73d873e1f542b59a0dee77785fef",
    "thumbnail": "https://b.thumbs.redditmedia.com/XBOut3RYerEuzVJvg10oQtuOHc2waXGWW9ujG5_RbJI.jpg"
  },
  "score": {
    "comments": 20,
    "downs": 0,
    "isCurated": false,
    "ratio": 0.99,
    "ups": 965,
    "value": 965
  },
  "subreddit": {
    "id": "t5_2xy5e",
    "name": "TerrainBuilding"
  },
  "tags": [],
  "title": "I was given the heads up that you guys may be interested in this little ‘treehouse’ I made for a house plant :)",
  "url": "https://www.reddit.com/r/TerrainBuilding/comments/g5ch9k/i_was_given_the_heads_up_that_you_guys_may_be/"
}
