{
  "author": {
    "id": "t2_41oh4",
    "name": "Impius"
  },
  "date": {
    "day": 1552694400,
    "full": 1552705645,
    "month": 1551398400,
    "week": 1552176000
  },
  "id": "t3_b1nu0t",
  "misc": {
    "postHint": "self"
  },
  "picture": {
    "full": "https://external-preview.redd.it/u-zHts2F-CxAL9iYg85jz9_UuyjDse0AT148boc9l0k.png?auto=webp&s=f1e6cd464b7a37565320f48d259aec2d206dc703",
    "preview": "https://external-preview.redd.it/u-zHts2F-CxAL9iYg85jz9_UuyjDse0AT148boc9l0k.png?width=640&crop=smart&auto=webp&s=5d18263c9486d98631e4eb480501a9c02a905eaa",
    "thumbnail": "self"
  },
  "score": {
    "comments": 2,
    "downs": 0,
    "isCurated": false,
    "ratio": 1,
    "ups": 2,
    "value": 2
  },
  "subreddit": {
    "id": "t5_2xy5e",
    "name": "TerrainBuilding"
  },
  "tags": [],
  "title": "First real attempt at building anything.",
  "url": "https://www.reddit.com/r/TerrainBuilding/comments/b1nu0t/first_real_attempt_at_building_anything/"
}
