{
  "author": {
    "id": "t2_cpxbd",
    "name": "TheCraghammer"
  },
  "date": {
    "day": 1391299200,
    "full": 1391369162,
    "month": 1391212800,
    "week": 1391299200
  },
  "id": "t3_1wts53",
  "misc": {
    "postHint": "link"
  },
  "picture": {
    "full": "https://external-preview.redd.it/YgAuu3qVpPmAXSXiqLD1_2tzzgeYUujfJt2h7RcdZeQ.jpg?auto=webp&s=4db8db290d77a046ed83f2b6be3423aac72954c4",
    "preview": "https://external-preview.redd.it/YgAuu3qVpPmAXSXiqLD1_2tzzgeYUujfJt2h7RcdZeQ.jpg?width=640&crop=smart&auto=webp&s=b55fc719d0c9c2db9eff039869c3ea4a7ae38eed",
    "thumbnail": "https://b.thumbs.redditmedia.com/gh4SG9csWBDiKcAEtJDah4otXjXKawMEFoa4-5YEerM.jpg"
  },
  "score": {
    "comments": 9,
    "downs": 0,
    "isCurated": false,
    "ratio": 0.98,
    "ups": 33,
    "value": 33
  },
  "subreddit": {
    "id": "t5_2xy5e",
    "name": "TerrainBuilding"
  },
  "tags": [],
  "title": "My first try at mini terrain, The Moon Shrine. Any tips you have would be great",
  "url": "https://www.reddit.com/r/TerrainBuilding/comments/1wts53/my_first_try_at_mini_terrain_the_moon_shrine_any/"
}
