{
  "author": {
    "id": "t2_bqlq5",
    "name": "Gamlin777"
  },
  "date": {
    "day": 1546905600,
    "full": 1546944282,
    "month": 1546300800,
    "week": 1546732800
  },
  "id": "t3_adt2he",
  "misc": {
    "postHint": "link"
  },
  "picture": {
    "full": "https://external-preview.redd.it/RQ2l17Gx7VqGPfkeCDrYXVRrwBgsbPxK7B3mgIIkjV0.jpg?auto=webp&s=cc63b7a4d6ffb66d9be51f0a81c63d638c30ce9f",
    "preview": "https://external-preview.redd.it/RQ2l17Gx7VqGPfkeCDrYXVRrwBgsbPxK7B3mgIIkjV0.jpg?width=640&crop=smart&auto=webp&s=118517e6c4152f71158041ca5e399d8d0dd1b7e5",
    "thumbnail": "https://b.thumbs.redditmedia.com/QiBmHRq30ae8QPWpJ-xmT8B72RzMNan4IfpVFnDq-2M.jpg"
  },
  "score": {
    "comments": 10,
    "downs": 0,
    "isCurated": false,
    "ratio": 0.99,
    "ups": 157,
    "value": 157
  },
  "subreddit": {
    "id": "t5_2xy5e",
    "name": "TerrainBuilding"
  },
  "tags": [],
  "title": "My First Piece of AoS Scenary: Ruined Tower",
  "url": "https://www.reddit.com/r/TerrainBuilding/comments/adt2he/my_first_piece_of_aos_scenary_ruined_tower/"
}
