{
  "author": {
    "id": "t2_5m560",
    "name": "AmandaWakefield"
  },
  "date": {
    "day": 1609804800,
    "full": 1609884661,
    "month": 1609459200,
    "week": 1609632000
  },
  "id": "t3_kr9675",
  "misc": {
    "postHint": "image"
  },
  "picture": {
    "full": "https://external-preview.redd.it/RYbE_A7g6qkkEq9wZQROwPlR7k7mgq9ixifapw1tEkk.jpg?auto=webp&s=26fc5558bdda369bf1217c491383bf78dfae68c5",
    "preview": "https://external-preview.redd.it/RYbE_A7g6qkkEq9wZQROwPlR7k7mgq9ixifapw1tEkk.jpg?width=640&crop=smart&auto=webp&s=184495ed4da56deefd16c8b1508b9ab348c4a437",
    "thumbnail": "https://b.thumbs.redditmedia.com/_qPgHUiDh0lXyX9jxQNtH8lEDJAS2p3T3jmAWZ2ZrAg.jpg"
  },
  "score": {
    "comments": 5,
    "downs": 0,
    "isCurated": false,
    "ratio": 0.99,
    "ups": 58,
    "value": 58
  },
  "subreddit": {
    "id": "t5_2xy5e",
    "name": "TerrainBuilding"
  },
  "tags": [],
  "title": "Tent and Bedroll scatter",
  "url": "https://www.reddit.com/r/TerrainBuilding/comments/kr9675/tent_and_bedroll_scatter/"
}
