{
  "author": {
    "id": "t2_7zw6b7b",
    "name": "Jward44553"
  },
  "date": {
    "day": 1579219200,
    "full": 1579280684,
    "month": 1577836800,
    "week": 1578787200
  },
  "id": "t3_eq34oc",
  "misc": {
    "postHint": "image"
  },
  "picture": {
    "full": "https://preview.redd.it/wiw97l8sedb41.jpg?auto=webp&s=29f8270a662350577edb7a2bf8c6f06aa2283207",
    "preview": "https://preview.redd.it/wiw97l8sedb41.jpg?width=640&crop=smart&auto=webp&s=7bfefa17eaa44e97b6f1105d548e53b46a490ea9",
    "thumbnail": "https://b.thumbs.redditmedia.com/28iv7Idr0lTOIsCOXo4CpY3eVq88A863Z0pnNsZ33RE.jpg"
  },
  "score": {
    "comments": 10,
    "downs": 0,
    "isCurated": false,
    "ratio": 0.98,
    "ups": 32,
    "value": 32
  },
  "subreddit": {
    "id": "t5_2xy5e",
    "name": "TerrainBuilding"
  },
  "tags": [],
  "title": "Gallows (wip) C&C welcome!",
  "url": "https://www.reddit.com/r/TerrainBuilding/comments/eq34oc/gallows_wip_cc_welcome/"
}
