{
  "author": {
    "id": "t2_33dh451y",
    "name": "kubikneon"
  },
  "date": {
    "day": 1566432000,
    "full": 1566438476,
    "month": 1564617600,
    "week": 1566086400
  },
  "id": "t3_ctqmvo",
  "misc": {
    "postHint": "link"
  },
  "picture": {
    "full": "https://external-preview.redd.it/TI-60xNBvtAaOdTCA0RAP1IwLUP9zqDWs0s0Zr29gdc.jpg?auto=webp&s=5b1613cb1e953a059420bb1f0bf4b248ead41e5c",
    "preview": "https://external-preview.redd.it/TI-60xNBvtAaOdTCA0RAP1IwLUP9zqDWs0s0Zr29gdc.jpg?width=640&crop=smart&auto=webp&s=d43e7a13f7a0804326f87e33226b7d7b8314c75a",
    "thumbnail": "https://b.thumbs.redditmedia.com/gVmNxAqcRMMOPajnZ2KNssPlZhcQbEHbLU2uwWONTOc.jpg"
  },
  "score": {
    "comments": 4,
    "downs": 0,
    "isCurated": false,
    "ratio": 0.97,
    "ups": 66,
    "value": 66
  },
  "subreddit": {
    "id": "t5_2xy5e",
    "name": "TerrainBuilding"
  },
  "tags": [],
  "title": "Making some Terrain Tutor style rocky hills. Still a bit more work to do.",
  "url": "https://www.reddit.com/r/TerrainBuilding/comments/ctqmvo/making_some_terrain_tutor_style_rocky_hills_still/"
}
