{
  "author": {
    "id": "t2_yesk6",
    "name": "diesel153368"
  },
  "date": {
    "day": 1584403200,
    "full": 1584477370,
    "month": 1583020800,
    "week": 1584230400
  },
  "id": "t3_fkckz7",
  "misc": {
    "postHint": "image"
  },
  "picture": {
    "full": "https://preview.redd.it/rrrav987nan41.jpg?auto=webp&s=6ad0d3e8f92e4a50ac7bfff97df3599c08ff22c6",
    "preview": "https://preview.redd.it/rrrav987nan41.jpg?width=640&crop=smart&auto=webp&s=bcf187873b8f4bc0430504896c73d8307d64e9e0",
    "thumbnail": "https://b.thumbs.redditmedia.com/2Lu2NkeAqJMX20FAckHo-bY86qKYYK-oViAFuu6idVE.jpg"
  },
  "score": {
    "comments": 26,
    "downs": 0,
    "isCurated": false,
    "ratio": 0.99,
    "ups": 867,
    "value": 867
  },
  "subreddit": {
    "id": "t5_2xy5e",
    "name": "TerrainBuilding"
  },
  "tags": [],
  "title": "Entered my first contest! Let me know what you think.",
  "url": "https://www.reddit.com/r/TerrainBuilding/comments/fkckz7/entered_my_first_contest_let_me_know_what_you/"
}
