{
  "author": {
    "id": "t2_tunql",
    "name": "the_largest_rodent"
  },
  "date": {
    "day": 1584230400,
    "full": 1584295580,
    "month": 1583020800,
    "week": 1584230400
  },
  "id": "t3_fj5jlb",
  "misc": {
    "postHint": "image"
  },
  "picture": {
    "full": "https://preview.redd.it/v1r17w7nmvm41.jpg?auto=webp&s=dfc816fccf67d2df0303f67287450e3ca54e535d",
    "preview": "https://preview.redd.it/v1r17w7nmvm41.jpg?width=640&crop=smart&auto=webp&s=bd34cf85e507d44a0e44383fc1f73bd24ba233af",
    "thumbnail": "https://b.thumbs.redditmedia.com/Q5_QuE56cG4qApBAyr0icJJ1jM1Rz1JvaHojoTV1bAg.jpg"
  },
  "score": {
    "comments": 7,
    "downs": 0,
    "isCurated": false,
    "ratio": 0.93,
    "ups": 21,
    "value": 21
  },
  "subreddit": {
    "id": "t5_2xy5e",
    "name": "TerrainBuilding"
  },
  "tags": [],
  "title": "Thanks for the advice! I think they look much more like coals now. The trick seemed to be more black around the edges and more orange in the middle. I’m ok with them now, but if anyone has any more advice let me know!",
  "url": "https://www.reddit.com/r/TerrainBuilding/comments/fj5jlb/thanks_for_the_advice_i_think_they_look_much_more/"
}
