{
  "author": {
    "id": "t2_4v6fw1q7",
    "name": "Urban_Printer"
  },
  "date": {
    "day": 1583020800,
    "full": 1583089114,
    "month": 1583020800,
    "week": 1583020800
  },
  "id": "t3_fbyoq5",
  "misc": {
    "postHint": "image"
  },
  "picture": {
    "full": "https://preview.redd.it/87w7ucw6z3k41.jpg?auto=webp&s=aff18eb432da35a73280c6bcd24e8610e80ca141",
    "preview": "https://preview.redd.it/87w7ucw6z3k41.jpg?width=640&crop=smart&auto=webp&s=4ef00d3e202dc266e951beeb5e4af08541661a89",
    "thumbnail": "https://b.thumbs.redditmedia.com/HRIXynmnPqauKTQ4zbjGpzJ_u59BmY_tc6wNVdYukic.jpg"
  },
  "score": {
    "comments": 32,
    "downs": 0,
    "isCurated": false,
    "ratio": 0.99,
    "ups": 765,
    "value": 765
  },
  "subreddit": {
    "id": "t5_2xy5e",
    "name": "TerrainBuilding"
  },
  "tags": [],
  "title": "Mud Trench - Progress Update #2",
  "url": "https://www.reddit.com/r/TerrainBuilding/comments/fbyoq5/mud_trench_progress_update_2/"
}
