{
  "author": {
    "id": "t2_vdpdh35",
    "name": "studiolevel"
  },
  "date": {
    "day": 1583539200,
    "full": 1583612552,
    "month": 1583020800,
    "week": 1583020800
  },
  "id": "t3_ff0wb9",
  "misc": {
    "postHint": "hosted:video"
  },
  "picture": {
    "full": "https://external-preview.redd.it/9RkJx3pz9YMZpeVThgU8WvgRcPXPmCsfmTcVwPlF4jM.png?format=pjpg&auto=webp&s=a8026c1fb7d8ddfd9be202b736dd4840b28da738",
    "preview": "https://external-preview.redd.it/9RkJx3pz9YMZpeVThgU8WvgRcPXPmCsfmTcVwPlF4jM.png?width=640&crop=smart&format=pjpg&auto=webp&s=8974f1f3c841e5660666637ddf6a0398c56926e4",
    "thumbnail": "https://b.thumbs.redditmedia.com/TS3VavxL54UlN2OXXykhpZlz3xiaGap5Mua01pNnl3I.jpg"
  },
  "score": {
    "comments": 6,
    "downs": 0,
    "isCurated": false,
    "ratio": 0.98,
    "ups": 104,
    "value": 104
  },
  "subreddit": {
    "id": "t5_2xy5e",
    "name": "TerrainBuilding"
  },
  "tags": [],
  "title": "PETROLYARD: Tabletop Modular Complex. This modular, creative and unique post-apocalyptic terrain will add flavor to your favorite zombie game.",
  "url": "https://www.reddit.com/r/TerrainBuilding/comments/ff0wb9/petrolyard_tabletop_modular_complex_this_modular/"
}
