{
  "author": {
    "id": "t2_f9k03ez",
    "name": "three-trees"
  },
  "date": {
    "day": 1576972800,
    "full": 1577050530,
    "month": 1575158400,
    "week": 1576972800
  },
  "id": "t3_eeaowd",
  "misc": {
    "postHint": "image"
  },
  "picture": {
    "full": "https://preview.redd.it/kgjfw1fmp8641.jpg?auto=webp&s=02974bed9275095a96a14a9cd83689b8d55bc1ea",
    "preview": "https://preview.redd.it/kgjfw1fmp8641.jpg?width=640&crop=smart&auto=webp&s=d711b56c65763025ccdf420e4ff25a56b5067585",
    "thumbnail": "https://b.thumbs.redditmedia.com/zs6qnA-1gxxbT4vdcNWBKbDfCOn9j1wDEKykyo4kGNk.jpg"
  },
  "score": {
    "comments": 39,
    "downs": 0,
    "isCurated": false,
    "ratio": 0.99,
    "ups": 564,
    "value": 564
  },
  "subreddit": {
    "id": "t5_2xy5e",
    "name": "TerrainBuilding"
  },
  "tags": [],
  "title": "My big project for most of the last year, a cavern tile set of over 100 pieces. Links to the step-by-step processes for the different tiles in the comments",
  "url": "https://www.reddit.com/r/TerrainBuilding/comments/eeaowd/my_big_project_for_most_of_the_last_year_a_cavern/"
}
