{
  "author": {
    "id": "t2_6h513",
    "name": "The_Bald"
  },
  "date": {
    "day": 1536278400,
    "full": 1536334883,
    "month": 1535760000,
    "week": 1535846400
  },
  "id": "t3_9dvjt9",
  "misc": {
    "postHint": "link"
  },
  "picture": {
    "full": "https://external-preview.redd.it/9xd_yWUuIh6WGQ1ndwgDiVwxIjv4m6M48qTC01huBig.jpg?auto=webp&s=f0a29a7f9cd2e3f743b55178345a6a7032873855",
    "preview": "https://external-preview.redd.it/9xd_yWUuIh6WGQ1ndwgDiVwxIjv4m6M48qTC01huBig.jpg?width=640&crop=smart&auto=webp&s=434f1bbca666532c1ce4799d71b21b97838fb774",
    "thumbnail": "https://b.thumbs.redditmedia.com/pK2S1McXyJ388C4KAsoiOLT1ktNCOMzrvqMUhUgO5Do.jpg"
  },
  "score": {
    "comments": 15,
    "downs": 0,
    "isCurated": false,
    "ratio": 0.98,
    "ups": 124,
    "value": 124
  },
  "subreddit": {
    "id": "t5_2xy5e",
    "name": "TerrainBuilding"
  },
  "tags": [],
  "title": "I wanted to try making a fantasy landscape with materials I (mostly) found outside -- 'Flight of the Deer Pixies'",
  "url": "https://www.reddit.com/r/TerrainBuilding/comments/9dvjt9/i_wanted_to_try_making_a_fantasy_landscape_with/"
}
