{
  "author": {
    "id": "t2_k2428",
    "name": "frostbittenteddy"
  },
  "date": {
    "day": 1537142400,
    "full": 1537211231,
    "month": 1535760000,
    "week": 1537056000
  },
  "id": "t3_9gn9lb",
  "misc": {
    "postHint": "link"
  },
  "picture": {
    "full": "https://external-preview.redd.it/pMSsRuraQgom949hjYdZrR75PAQ15gmi0lF_q_ZFovo.jpg?auto=webp&s=66dbc033812343d06d317262ab05650c50c3765e",
    "preview": "https://external-preview.redd.it/pMSsRuraQgom949hjYdZrR75PAQ15gmi0lF_q_ZFovo.jpg?width=640&crop=smart&auto=webp&s=acc089828feddd0baf581beb2daa6eaacde9155e",
    "thumbnail": "https://a.thumbs.redditmedia.com/NtyZXypW8HNaDXqG2vJHykMsXPtugp1mt8yX_LsAwv8.jpg"
  },
  "score": {
    "comments": 10,
    "downs": 0,
    "isCurated": false,
    "ratio": 0.94,
    "ups": 57,
    "value": 57
  },
  "subreddit": {
    "id": "t5_2xy5e",
    "name": "TerrainBuilding"
  },
  "tags": [],
  "title": "Shipwreck for a little Titanicus Diorama I'm building. What do you guys think? I'm not particularly adept with Plasticard so any input is appreciated",
  "url": "https://www.reddit.com/r/TerrainBuilding/comments/9gn9lb/shipwreck_for_a_little_titanicus_diorama_im/"
}
