{
  "author": {
    "id": "t2_ceud74i",
    "name": "RowenMorland"
  },
  "date": {
    "day": 1568332800,
    "full": 1568393693,
    "month": 1567296000,
    "week": 1567900800
  },
  "id": "t3_d3s4q3",
  "misc": {
    "postHint": "image"
  },
  "picture": {
    "full": "https://external-preview.redd.it/sh91aCPG86uRBdG3opkBkmsS6C3cqAmeJk1_e6nVzGA.jpg?auto=webp&s=17f8bd903a21bde140eee479a86997fee54b0123",
    "preview": "https://external-preview.redd.it/sh91aCPG86uRBdG3opkBkmsS6C3cqAmeJk1_e6nVzGA.jpg?width=640&crop=smart&auto=webp&s=825fe65b08bff7b9d0a1163ab3b891dcc44e237e",
    "thumbnail": "https://b.thumbs.redditmedia.com/BzJUklvQu2UJjNhzc1GWpQYyQr4q_7nNtkzNI-Wxzgk.jpg"
  },
  "score": {
    "comments": 2,
    "downs": 0,
    "isCurated": false,
    "ratio": 0.9,
    "ups": 35,
    "value": 35
  },
  "subreddit": {
    "id": "t5_2xy5e",
    "name": "TerrainBuilding"
  },
  "tags": [],
  "title": "Had time to paint and flock this.",
  "url": "https://www.reddit.com/r/TerrainBuilding/comments/d3s4q3/had_time_to_paint_and_flock_this/"
}
