{
  "author": {
    "id": "t2_5e1ct",
    "name": "Ralltir"
  },
  "date": {
    "day": 1594252800,
    "full": 1594332020,
    "month": 1593561600,
    "week": 1593907200
  },
  "id": "t3_hoccax",
  "misc": {
    "postHint": "image"
  },
  "picture": {
    "full": "https://preview.redd.it/8tw2vrb1mw951.jpg?auto=webp&s=bb5af159e18be677d033a495c23f4a6adbc008fc",
    "preview": "https://preview.redd.it/8tw2vrb1mw951.jpg?width=640&crop=smart&auto=webp&s=ac847aaa58af7c8b364cc7c6d775a7561aac60de",
    "thumbnail": "https://b.thumbs.redditmedia.com/8lbVGF6flc_vDqtDm9HGfYGQV2j1FEhuz_ycmuTSakY.jpg"
  },
  "score": {
    "comments": 0,
    "downs": 0,
    "isCurated": false,
    "ratio": 0.97,
    "ups": 32,
    "value": 32
  },
  "subreddit": {
    "id": "t5_2xy5e",
    "name": "TerrainBuilding"
  },
  "tags": [],
  "title": "PC view of inside a WIP tavern",
  "url": "https://www.reddit.com/r/TerrainBuilding/comments/hoccax/pc_view_of_inside_a_wip_tavern/"
}
