{
  "author": {
    "id": "t2_ob7x9",
    "name": "WolvoNeil"
  },
  "date": {
    "day": 1594857600,
    "full": 1594913746,
    "month": 1593561600,
    "week": 1594512000
  },
  "id": "t3_hsbrkd",
  "misc": {
    "postHint": "link"
  },
  "picture": {
    "full": "https://external-preview.redd.it/46fCSUnmLENrkTynYPsuIPBr-vHoQM4JvEwMQBDh1X0.jpg?auto=webp&s=bb67aa672d2c7bba39d7a502aab7a9023d197bd4",
    "preview": "https://external-preview.redd.it/46fCSUnmLENrkTynYPsuIPBr-vHoQM4JvEwMQBDh1X0.jpg?width=640&crop=smart&auto=webp&s=33c91a37683b39e70466976faf7e775fa9211a5d",
    "thumbnail": "https://b.thumbs.redditmedia.com/VAQWsLtcWiqhymCGeeAnHTd_P_uzbH7ibWJWjg4TliQ.jpg"
  },
  "score": {
    "comments": 3,
    "downs": 0,
    "isCurated": false,
    "ratio": 0.96,
    "ups": 30,
    "value": 30
  },
  "subreddit": {
    "id": "t5_2xy5e",
    "name": "TerrainBuilding"
  },
  "tags": [],
  "title": "Somewhere in Holland 1944 - Culmination of my recent work",
  "url": "https://www.reddit.com/r/TerrainBuilding/comments/hsbrkd/somewhere_in_holland_1944_culmination_of_my/"
}
