{
  "author": {
    "id": "t2_e6u9fr",
    "name": "abscnth"
  },
  "date": {
    "day": 1595462400,
    "full": 1595493842,
    "month": 1593561600,
    "week": 1595116800
  },
  "id": "t3_hwc7mt",
  "misc": {
    "postHint": "image"
  },
  "picture": {
    "full": "https://preview.redd.it/ir7v53rtkkc51.png?auto=webp&s=14efa71fc716760f2a49ada2a3ff365590c39361",
    "preview": "https://preview.redd.it/ir7v53rtkkc51.png?width=640&crop=smart&auto=webp&s=7ff4eb309ba26a0bee3c62c109189a555c1017e1",
    "thumbnail": "https://b.thumbs.redditmedia.com/NlLVJRzO6CQX50KILrzPjrOvtwRFtd_Pw6B9lWpD1RU.jpg"
  },
  "score": {
    "comments": 0,
    "downs": 0,
    "isCurated": false,
    "ratio": 0.91,
    "ups": 24,
    "value": 24
  },
  "subreddit": {
    "id": "t5_2xy5e",
    "name": "TerrainBuilding"
  },
  "tags": [],
  "title": "WIP on my enchanted forest set",
  "url": "https://www.reddit.com/r/TerrainBuilding/comments/hwc7mt/wip_on_my_enchanted_forest_set/"
}
