{
  "author": {
    "id": "t2_1l30vlh1",
    "name": "SpaceDruss"
  },
  "date": {
    "day": 1595635200,
    "full": 1595712744,
    "month": 1593561600,
    "week": 1595116800
  },
  "id": "t3_hxunuq",
  "misc": {
    "postHint": "image"
  },
  "picture": {
    "full": "https://preview.redd.it/xsx4cwvon2d51.jpg?auto=webp&s=61ad57b7000d1841594fb9bc41edfea54b5d25db",
    "preview": "https://preview.redd.it/xsx4cwvon2d51.jpg?width=640&crop=smart&auto=webp&s=4a1c2f0fadd51297729cec71f25186f5258fd1f8",
    "thumbnail": "https://a.thumbs.redditmedia.com/XpJY2t2NFkzGWrU6U7YoRYxWVxaakLvRz83pYNslBg8.jpg"
  },
  "score": {
    "comments": 1,
    "downs": 0,
    "isCurated": false,
    "ratio": 0.98,
    "ups": 44,
    "value": 44
  },
  "subreddit": {
    "id": "t5_2xy5e",
    "name": "TerrainBuilding"
  },
  "tags": [],
  "title": "Another quick pick of my building from earlier, this shows the top and inside of the build, this upper floor is removable and sits in place with magnets to easily access the inside of the build. Video in comments",
  "url": "https://www.reddit.com/r/TerrainBuilding/comments/hxunuq/another_quick_pick_of_my_building_from_earlier/"
}
