{
  "author": {
    "id": "t2_6ir5ta2s",
    "name": "Ikki1024"
  },
  "date": {
    "day": 1590105600,
    "full": 1590168159,
    "month": 1588291200,
    "week": 1589673600
  },
  "id": "t3_gonk9v",
  "misc": {
    "postHint": "image"
  },
  "picture": {
    "full": "https://preview.redd.it/hemzw8stoc051.jpg?auto=webp&s=5ebf3f7eb9401de96c90cae3c0fb4091f54e12c5",
    "preview": "https://preview.redd.it/hemzw8stoc051.jpg?width=640&crop=smart&auto=webp&s=9df980eb716530105182acf3a9b2ef475d6ea878",
    "thumbnail": "https://b.thumbs.redditmedia.com/QGiegBXMSnRCmu8fNtOgYUMLZ3Bd3O597MP2qcF1N_g.jpg"
  },
  "score": {
    "comments": 3,
    "downs": 0,
    "isCurated": false,
    "ratio": 1,
    "ups": 21,
    "value": 21
  },
  "subreddit": {
    "id": "t5_2xy5e",
    "name": "TerrainBuilding"
  },
  "tags": [],
  "title": "First attempt at furniture and accessories.",
  "url": "https://www.reddit.com/r/TerrainBuilding/comments/gonk9v/first_attempt_at_furniture_and_accessories/"
}
