{
  "author": {
    "id": "t2_106mw9xf",
    "name": "modellismofantasy"
  },
  "date": {
    "day": 1588982400,
    "full": 1589059533,
    "month": 1588291200,
    "week": 1588464000
  },
  "id": "t3_ggo1sp",
  "misc": {
    "postHint": "image"
  },
  "picture": {
    "full": "https://preview.redd.it/wrlzhe294tx41.jpg?auto=webp&s=aa7ac8cd2167c3f1f759f6cb09fc3a704d14cb93",
    "preview": "https://preview.redd.it/wrlzhe294tx41.jpg?width=640&crop=smart&auto=webp&s=b207ea5d66dc5aeb486450a847ad9637400a3717",
    "thumbnail": "https://a.thumbs.redditmedia.com/5sM_lFWA8WpUASjtsRESdvJ5FZvRyKjPfrzuJyCpKZ0.jpg"
  },
  "score": {
    "comments": 1,
    "downs": 0,
    "isCurated": false,
    "ratio": 0.92,
    "ups": 11,
    "value": 11
  },
  "subreddit": {
    "id": "t5_2xy5e",
    "name": "TerrainBuilding"
  },
  "tags": [],
  "title": "Trunk. Handmade in XPS foam. Other in the comments",
  "url": "https://www.reddit.com/r/TerrainBuilding/comments/ggo1sp/octrunk_handmade_in_xps_foam_other_in_the_comments/"
}
