{
  "author": {
    "id": "t2_7l9jj",
    "name": "TheDragisal"
  },
  "date": {
    "day": 1441843200,
    "full": 1441908677,
    "month": 1441065600,
    "week": 1441497600
  },
  "id": "t3_3kfmlc",
  "misc": {
    "postHint": "link"
  },
  "picture": {
    "full": "https://external-preview.redd.it/soFXwyMl4RYHhGR1-wd-kzECxeOCj7wM0TC7msTDUdk.jpg?auto=webp&s=22cd1d1b525b143bbe0083f8f3a719763a645ead",
    "preview": "https://external-preview.redd.it/soFXwyMl4RYHhGR1-wd-kzECxeOCj7wM0TC7msTDUdk.jpg?width=640&crop=smart&auto=webp&s=a2f0dea0b92ca6fe38d56a50e1fda57d722dbbcf",
    "thumbnail": "https://b.thumbs.redditmedia.com/fmZWUbYV-fFWHacTC86K6YEeJt09gxTcxfB8LpbO2Kc.jpg"
  },
  "score": {
    "comments": 7,
    "downs": 0,
    "isCurated": false,
    "ratio": 0.91,
    "ups": 38,
    "value": 38
  },
  "subreddit": {
    "id": "t5_2xy5e",
    "name": "TerrainBuilding"
  },
  "tags": [],
  "title": "Tyranid Spawning pool. Early WiP",
  "url": "https://www.reddit.com/r/TerrainBuilding/comments/3kfmlc/tyranid_spawning_pool_early_wip/"
}
