{
  "author": {
    "id": "t2_909c5",
    "name": "GejmaBobs"
  },
  "date": {
    "day": 1403136000,
    "full": 1403204934,
    "month": 1401580800,
    "week": 1402790400
  },
  "id": "t3_28kr1k",
  "misc": {
    "postHint": "link"
  },
  "picture": {
    "full": "https://external-preview.redd.it/2Z43VYN50xuCi0w2vm0qWeXX_wdkig2_eBj4qse-4Z8.jpg?auto=webp&s=9812c9bbe5a289e0aa10fcc72ede4b8b888795a8",
    "preview": "https://external-preview.redd.it/2Z43VYN50xuCi0w2vm0qWeXX_wdkig2_eBj4qse-4Z8.jpg?width=640&crop=smart&auto=webp&s=aea524029735153e86ecf15c4b7f8d076b09f010",
    "thumbnail": "https://b.thumbs.redditmedia.com/9SkatXuQBbMfnHaJhYR5ZdkiLne0GWv9Ci5uaSpZjrk.jpg"
  },
  "score": {
    "comments": 2,
    "downs": 0,
    "isCurated": false,
    "ratio": 0.91,
    "ups": 8,
    "value": 8
  },
  "subreddit": {
    "id": "t5_2xy5e",
    "name": "TerrainBuilding"
  },
  "tags": [],
  "title": "X-post from /r/warhammer40k some WIP terrain",
  "url": "https://www.reddit.com/r/TerrainBuilding/comments/28kr1k/xpost_from_rwarhammer40k_some_wip_terrain/"
}
