{
  "author": {
    "id": "t2_ir4j0",
    "name": "darkPrince010"
  },
  "date": {
    "day": 1466812800,
    "full": 1466822667,
    "month": 1464739200,
    "week": 1466294400
  },
  "id": "t3_4pqmq9",
  "misc": {
    "postHint": "link"
  },
  "picture": {
    "full": "https://external-preview.redd.it/xwEu8Ega39v3xCjchJH8iV61AVBr_egAFXHvDxPflJk.jpg?auto=webp&s=574cb62e0dbbf90a04c46a05d50e4a2b52ac432b",
    "preview": "https://external-preview.redd.it/xwEu8Ega39v3xCjchJH8iV61AVBr_egAFXHvDxPflJk.jpg?width=640&crop=smart&auto=webp&s=48b688db4b9ab28ed648b73c5cd5af7489b9e5d3",
    "thumbnail": "https://a.thumbs.redditmedia.com/aCGjYuRUmJb6PFtPSedGS2_7qkEbrPpXrwofhFZjko8.jpg"
  },
  "score": {
    "comments": 3,
    "downs": 0,
    "isCurated": false,
    "ratio": 0.89,
    "ups": 24,
    "value": 24
  },
  "subreddit": {
    "id": "t5_2xy5e",
    "name": "TerrainBuilding"
  },
  "tags": [],
  "title": "Full City Skirmish Terrain WIP, Part 11.5",
  "url": "https://www.reddit.com/r/TerrainBuilding/comments/4pqmq9/xpost_from_rironwatchmagazine_full_city_skirmish/"
}
