{
  "author": {
    "id": "t2_gld0j",
    "name": "TeamTallahassee"
  },
  "date": {
    "day": 1559952000,
    "full": 1560020672,
    "month": 1559347200,
    "week": 1559433600
  },
  "id": "t3_bybch0",
  "misc": {
    "postHint": "link"
  },
  "picture": {
    "full": "https://external-preview.redd.it/la74fCvcTEh5U4wAceli-BMisbU0sbf6MFDBEvz8IWg.jpg?auto=webp&s=6564801925a1c6070ada6634a20e95ca95e99371",
    "preview": "https://external-preview.redd.it/la74fCvcTEh5U4wAceli-BMisbU0sbf6MFDBEvz8IWg.jpg?width=640&crop=smart&auto=webp&s=cc9d0b98465a1e9f7e19231583dcbc7bc8e5d133",
    "thumbnail": "https://b.thumbs.redditmedia.com/KVfiHW6SBJgbYWEr4AjB6BFtlBnzWy750ntqQWztqns.jpg"
  },
  "score": {
    "comments": 24,
    "downs": 0,
    "isCurated": false,
    "ratio": 0.99,
    "ups": 161,
    "value": 161
  },
  "subreddit": {
    "id": "t5_2xy5e",
    "name": "TerrainBuilding"
  },
  "tags": [],
  "title": "I've got some painting to do...",
  "url": "https://www.reddit.com/r/TerrainBuilding/comments/bybch0/ive_got_some_painting_to_do/"
}
