{
  "author": {
    "id": "t2_eg7fex1",
    "name": "TheRealRotochron"
  },
  "date": {
    "day": 1551312000,
    "full": 1551322703,
    "month": 1548979200,
    "week": 1550966400
  },
  "id": "t3_avm0v0",
  "misc": {
    "postHint": "image"
  },
  "picture": {
    "full": "https://preview.redd.it/he0lh2pe38j21.jpg?auto=webp&s=143328a1436184c76c1b6d65c9082b534b170887",
    "preview": "https://preview.redd.it/he0lh2pe38j21.jpg?width=640&crop=smart&auto=webp&s=f6cd18a8e83c1edfc81b26a99c99da6ba26531d7",
    "thumbnail": "https://b.thumbs.redditmedia.com/R-Z3RUj14iuPdg5p_OYx6whhJf2qf1rg3_bolGBpGcM.jpg"
  },
  "score": {
    "comments": 6,
    "downs": 0,
    "isCurated": false,
    "ratio": 0.99,
    "ups": 240,
    "value": 240
  },
  "subreddit": {
    "id": "t5_2xy5e",
    "name": "TerrainBuilding"
  },
  "tags": [],
  "title": "My first building! Playable interior, no interior walls. Dwarf for scale!",
  "url": "https://www.reddit.com/r/TerrainBuilding/comments/avm0v0/my_first_building_playable_interior_no_interior/"
}
