{
  "author": {
    "id": "t2_pqfix",
    "name": "-MatthiasR-"
  },
  "date": {
    "day": 1549497600,
    "full": 1549536044,
    "month": 1548979200,
    "week": 1549152000
  },
  "id": "t3_ao2hfg",
  "misc": {
    "postHint": "image"
  },
  "picture": {
    "full": "https://preview.redd.it/dsjgimtnk4f21.jpg?auto=webp&s=3a41832f5b8cc1dd67811a28dbaacb3e0e60685b",
    "preview": "https://preview.redd.it/dsjgimtnk4f21.jpg?width=640&crop=smart&auto=webp&s=849e5acaec298d97fdf7842a9950c51c6ab5418d",
    "thumbnail": "https://b.thumbs.redditmedia.com/yhXH7cKFfpTSNneMfs6yf2QdO0aGyJguqfm9nucwMTc.jpg"
  },
  "score": {
    "comments": 1,
    "downs": 0,
    "isCurated": false,
    "ratio": 0.93,
    "ups": 12,
    "value": 12
  },
  "subreddit": {
    "id": "t5_2xy5e",
    "name": "TerrainBuilding"
  },
  "tags": [],
  "title": "Statue of Tiamat",
  "url": "https://www.reddit.com/r/TerrainBuilding/comments/ao2hfg/statue_of_tiamat/"
}
